examples/text_generation.py
horde_client/__init__.py
horde_client/client.py
horde_client/config.py
horde_client/model.py
horde_client/utility.py
horde_client_rahuldshetty-1.0.0.dist-info/LICENSE
horde_client_rahuldshetty-1.0.0.dist-info/METADATA
horde_client_rahuldshetty-1.0.0.dist-info/WHEEL
horde_client_rahuldshetty-1.0.0.dist-info/top_level.txt
horde_client_rahuldshetty-1.0.0.dist-info/RECORD
