Metadata-Version: 2.1
Name: horde-client-rahuldshetty
Version: 1.0.0
Summary: Easy-to-use Python Interface for KoboldAI Horde.
Home-page: https://github.com/rahuldshetty/horde-client.git
Author: Rahul D Shettu
Author-email: Rahul D Shetty <35rahuldshetty@gmail.com>
Project-URL: Homepage, https://github.com/rahuldshetty/horde-client
Project-URL: Bug Tracker, https://github.com/rahuldshetty/horde-client/issues
Classifier: Programming Language :: Python :: 3
Classifier: License :: OSI Approved :: MIT License
Classifier: Operating System :: OS Independent
Requires-Python: >=3.7
License-File: LICENSE
Requires-Dist: requests ==2.27.1
Requires-Dist: pydantic ==2.3.0
